{
  "friends": [
    {
      "No.": "1",
      "First Name": "Kirstin",
      "Surname": "Gyasi",
      "Nationality": "Ghanaian",
      "Hometown": "Akropong"
    },
    {
      "No.": "2",
      "First Name": "Belinda",
      "Surname": "Amponsah",
      "Nationality": "Ghanaian",
      "Hometown": "Abiriw"
    },
    {
      "No.": "3",
      "First Name": "Sherene",
      "Surname": "Dankwah",
      "Nationality": "Ghanaian",
      "Hometown": "Abuakwa"
    },
    {
      "No.": "4",
      "First Name": "Desmond",
      "Surname": "Ayodele",
      "Nationality": "Nigerian",
      "Hometown": "Osusu"
    },
    {
      "No.": "5",
      "First Name": "Richard",
      "Surname": "Ehimwenman",
      "Nationality": "Nigerian",
      "Hometown": "Eziama"
    },
	{
      "No.": "6",
      "First Name": "Padiki",
      "Surname": "Hayfron",
      "Nationality": "Kenyan",
      "Hometown": "Nakuru"
    }
  ]
}
